{
  "asOfDate": "2026-06-15",
  "defaultYear": 2026,
  "defaultMonth": 6,
  "income": {
    "id": 1,
    "pay_frequency": "semi_monthly",
    "monthly_amount": null,
    "pay_day": null,
    "cutoff_1_day": 15,
    "cutoff_1_amount": 25000,
    "cutoff_2_day": 28,
    "cutoff_2_amount": 25000,
    "updated_at": "2026-06-01T00:00:00"
  },
  "cards": [
    {
      "id": 1,
      "nickname": "BDO Visa",
      "card_type": "credit_card",
      "credit_limit": 26200,
      "balance": 20479.35,
      "minimum_due": 1200,
      "due_day": 12,
      "is_active": true,
      "created_at": "2026-01-10T00:00:00",
      "updated_at": "2026-06-10T00:00:00"
    },
    {
      "id": 2,
      "nickname": "Payroll ATM",
      "card_type": "debit_card",
      "credit_limit": null,
      "balance": 8450,
      "minimum_due": null,
      "due_day": null,
      "is_active": true,
      "created_at": "2026-02-01T00:00:00",
      "updated_at": "2026-06-14T00:00:00"
    },
    {
      "id": 3,
      "nickname": "GCash",
      "card_type": "online_card",
      "credit_limit": null,
      "balance": 3200,
      "minimum_due": null,
      "due_day": null,
      "is_active": true,
      "created_at": "2026-03-01T00:00:00",
      "updated_at": "2026-06-14T00:00:00"
    }
  ],
  "occurrences": [
    {
      "id": 101,
      "debt_id": 1,
      "debt_name": "BDO Visa",
      "debt_type": "credit_card",
      "year": 2026,
      "month": 6,
      "due_date": "2026-06-12",
      "amount": 1200,
      "scheduled_amount": 1200,
      "statement_balance": 20479.35,
      "minimum_due": 1200,
      "credit_limit": 26200,
      "is_paid": false,
      "paid_at": null,
      "status": "overdue"
    },
    {
      "id": 102,
      "debt_id": 2,
      "debt_name": "Rent",
      "debt_type": "rent",
      "year": 2026,
      "month": 6,
      "due_date": "2026-06-05",
      "amount": 15000,
      "scheduled_amount": 15000,
      "statement_balance": null,
      "minimum_due": null,
      "credit_limit": null,
      "is_paid": true,
      "paid_at": "2026-06-04T10:00:00",
      "status": "paid"
    },
    {
      "id": 103,
      "debt_id": 3,
      "debt_name": "Atome - Laptop",
      "debt_type": "bnpl",
      "year": 2026,
      "month": 6,
      "due_date": "2026-06-18",
      "amount": 2500,
      "scheduled_amount": 3333.33,
      "statement_balance": null,
      "minimum_due": null,
      "credit_limit": null,
      "is_paid": false,
      "paid_at": null,
      "status": "pending"
    },
    {
      "id": 104,
      "debt_id": 4,
      "debt_name": "GLoan RYQW1715",
      "debt_type": "loan",
      "year": 2026,
      "month": 6,
      "due_date": "2026-06-25",
      "amount": 3500,
      "scheduled_amount": 5200,
      "statement_balance": null,
      "minimum_due": null,
      "credit_limit": null,
      "is_paid": false,
      "paid_at": null,
      "status": "pending"
    },
    {
      "id": 105,
      "debt_id": 5,
      "debt_name": "Meralco",
      "debt_type": "utility",
      "year": 2026,
      "month": 6,
      "due_date": "2026-06-22",
      "amount": 2800,
      "scheduled_amount": 2800,
      "statement_balance": null,
      "minimum_due": null,
      "credit_limit": null,
      "is_paid": false,
      "paid_at": null,
      "status": "pending"
    },
    {
      "id": 106,
      "debt_id": 6,
      "debt_name": "Netflix",
      "debt_type": "subscription",
      "year": 2026,
      "month": 6,
      "due_date": "2026-06-10",
      "amount": 549,
      "scheduled_amount": 549,
      "statement_balance": null,
      "minimum_due": null,
      "credit_limit": null,
      "is_paid": true,
      "paid_at": "2026-06-09T08:00:00",
      "status": "paid"
    },
    {
      "id": 201,
      "debt_id": 1,
      "debt_name": "BDO Visa",
      "debt_type": "credit_card",
      "year": 2026,
      "month": 7,
      "due_date": "2026-07-12",
      "amount": 1200,
      "scheduled_amount": 1200,
      "statement_balance": 19279.35,
      "minimum_due": 1200,
      "credit_limit": 26200,
      "is_paid": false,
      "paid_at": null,
      "status": "pending"
    },
    {
      "id": 202,
      "debt_id": 2,
      "debt_name": "Rent",
      "debt_type": "rent",
      "year": 2026,
      "month": 7,
      "due_date": "2026-07-05",
      "amount": 15000,
      "scheduled_amount": 15000,
      "statement_balance": null,
      "minimum_due": null,
      "credit_limit": null,
      "is_paid": false,
      "paid_at": null,
      "status": "pending"
    },
    {
      "id": 203,
      "debt_id": 3,
      "debt_name": "Atome - Laptop",
      "debt_type": "bnpl",
      "year": 2026,
      "month": 7,
      "due_date": "2026-07-18",
      "amount": 3333.33,
      "scheduled_amount": 3333.33,
      "statement_balance": null,
      "minimum_due": null,
      "credit_limit": null,
      "is_paid": false,
      "paid_at": null,
      "status": "pending"
    }
  ],
  "monthlyHistory": [
    { "year": 2025, "month": 7, "total": 18200, "paid": 18200, "unpaid": 0 },
    { "year": 2025, "month": 8, "total": 19100, "paid": 19100, "unpaid": 0 },
    { "year": 2025, "month": 9, "total": 20500, "paid": 19800, "unpaid": 700 },
    { "year": 2025, "month": 10, "total": 21000, "paid": 21000, "unpaid": 0 },
    { "year": 2025, "month": 11, "total": 22400, "paid": 22400, "unpaid": 0 },
    { "year": 2025, "month": 12, "total": 24800, "paid": 24000, "unpaid": 800 },
    { "year": 2026, "month": 1, "total": 23500, "paid": 23500, "unpaid": 0 },
    { "year": 2026, "month": 2, "total": 24100, "paid": 24100, "unpaid": 0 },
    { "year": 2026, "month": 3, "total": 25200, "paid": 24500, "unpaid": 700 },
    { "year": 2026, "month": 4, "total": 25800, "paid": 25800, "unpaid": 0 },
    { "year": 2026, "month": 5, "total": 26100, "paid": 25500, "unpaid": 600 },
    { "year": 2026, "month": 6, "total": 25549, "paid": 15549, "unpaid": 10000 }
  ]
}
